{
  "timestamp": "2025-12-24T19:31:52.159Z",
  "summary": {
    "total": 27,
    "critical": 27,
    "warnings": 0,
    "byType": {
      "redirect_link": 27
    }
  },
  "issues": [
    {
      "type": "redirect_link",
      "severity": "critical",
      "page": "/blue-cross-blue-shield-blue-cross-blue-shield-coverage",
      "details": "Internal link redirects to: http://localhost:5000/blue-cross-blue-shield-therapy-orlando"
    },
    {
      "type": "redirect_link",
      "severity": "critical",
      "page": "/aetna-aetna-coverage",
      "details": "Internal link redirects to: http://localhost:5000/psychiatrist-orlando-accepts-aetna"
    },
    {
      "type": "redirect_link",
      "severity": "critical",
      "page": "/optum-coverage",
      "details": "Internal link redirects to: http://localhost:5000/insurance"
    },
    {
      "type": "redirect_link",
      "severity": "critical",
      "page": "/cigna-coverage",
      "details": "Internal link redirects to: http://localhost:5000/psychiatrist-orlando-accepts-cigna"
    },
    {
      "type": "redirect_link",
      "severity": "critical",
      "page": "/adventhealth-coverage",
      "details": "Internal link redirects to: http://localhost:5000/insurance"
    },
    {
      "type": "redirect_link",
      "severity": "critical",
      "page": "/medication-management",
      "details": "Internal link redirects to: http://localhost:5000/services"
    },
    {
      "type": "redirect_link",
      "severity": "critical",
      "page": "/anxiety-treatment",
      "details": "Internal link redirects to: http://localhost:5000/anxiety-therapy"
    },
    {
      "type": "redirect_link",
      "severity": "critical",
      "page": "/anger-management",
      "details": "Internal link redirects to: http://localhost:5000/therapy"
    },
    {
      "type": "redirect_link",
      "severity": "critical",
      "page": "/esa-letter",
      "details": "Internal link redirects to: http://localhost:5000/services"
    },
    {
      "type": "redirect_link",
      "severity": "critical",
      "page": "/anxiety-disorders",
      "details": "Internal link redirects to: http://localhost:5000/anxiety-therapy"
    },
    {
      "type": "redirect_link",
      "severity": "critical",
      "page": "/depression",
      "details": "Internal link redirects to: http://localhost:5000/depression-treatment"
    },
    {
      "type": "redirect_link",
      "severity": "critical",
      "page": "/bipolar-disorder",
      "details": "Internal link redirects to: http://localhost:5000/bipolar-disorder-treatment"
    },
    {
      "type": "redirect_link",
      "severity": "critical",
      "page": "/ptsd-trauma",
      "details": "Internal link redirects to: http://localhost:5000/anxiety-therapy"
    },
    {
      "type": "redirect_link",
      "severity": "critical",
      "page": "/personality-disorders",
      "details": "Internal link redirects to: http://localhost:5000/services"
    },
    {
      "type": "redirect_link",
      "severity": "critical",
      "page": "/adhd-attention-deficit-hyperactivity-disorder",
      "details": "Internal link redirects to: http://localhost:5000/adhd-treatment"
    },
    {
      "type": "redirect_link",
      "severity": "critical",
      "page": "/eating-disorders",
      "details": "Internal link redirects to: http://localhost:5000/services"
    },
    {
      "type": "redirect_link",
      "severity": "critical",
      "page": "/schizophrenia-psychotic-disorders",
      "details": "Internal link redirects to: http://localhost:5000/services"
    },
    {
      "type": "redirect_link",
      "severity": "critical",
      "page": "/blog/open-relationship-guide",
      "details": "Internal link redirects to: http://localhost:5000/blog"
    },
    {
      "type": "redirect_link",
      "severity": "critical",
      "page": "/blog/understanding-social-exhaustion-adhd-brain",
      "details": "Internal link redirects to: http://localhost:5000/blog"
    },
    {
      "type": "redirect_link",
      "severity": "critical",
      "page": "/blog/prodromal-stage-mental-health",
      "details": "Internal link redirects to: http://localhost:5000/blog"
    },
    {
      "type": "redirect_link",
      "severity": "critical",
      "page": "/blog/ltr-relationship-meaning-guide",
      "details": "Internal link redirects to: http://localhost:5000/blog"
    },
    {
      "type": "redirect_link",
      "severity": "critical",
      "page": "/blog/reactive-attachment-disorder-in-adults",
      "details": "Internal link redirects to: http://localhost:5000/blog"
    },
    {
      "type": "redirect_link",
      "severity": "critical",
      "page": "/blog/nervous-breakdown",
      "details": "Internal link redirects to: http://localhost:5000/blog/what-is-mental-breakdown"
    },
    {
      "type": "redirect_link",
      "severity": "critical",
      "page": "/blog/how-to-get-over-someone-and-move-on-with-your-life",
      "details": "Internal link redirects to: http://localhost:5000/blog"
    },
    {
      "type": "redirect_link",
      "severity": "critical",
      "page": "/blog/lgbtqia2s-identity-explained",
      "details": "Internal link redirects to: http://localhost:5000/blog"
    },
    {
      "type": "redirect_link",
      "severity": "critical",
      "page": "/blog/signs-of-attention-seeking-behavior",
      "details": "Internal link redirects to: http://localhost:5000/blog"
    },
    {
      "type": "redirect_link",
      "severity": "critical",
      "page": "/blog/what-is-time-blindness",
      "details": "Internal link redirects to: http://localhost:5000/blog"
    }
  ]
}